rs3_api/__init__.py
rs3_api/bestiary.py
rs3_api/endpoints.py
rs3_api/grand_exchange.py
rs3_api/hiscores.py
rs3_api/models.py
rs3_api/runemetrics.py
rs3_api/httpService/__init__.py
rs3_api/httpService/http_request.py
rs3_api/utils/__init__.py
rs3_api/utils/jagex.py
tests/__init__.py
tests/test_bestiary.py
tests/test_grandexchange.py
tests/test_hiscores.py
tests/test_runemetrics.py
runescape3_api-2.0.0.dist-info/LICENSE
runescape3_api-2.0.0.dist-info/METADATA
runescape3_api-2.0.0.dist-info/WHEEL
runescape3_api-2.0.0.dist-info/top_level.txt
runescape3_api-2.0.0.dist-info/RECORD
