Metadata-Version: 2.1
Name: runescape3-api
Version: 2.0.0
Summary: runescape3-api is an open-source wrapper, that allows interaction with the various APIs available for the popular MMORPG RuneScape3
Home-page: https://gitlab.com/ballioli/runescape3-api
Author: Baldur Óli Barkarson
Author-email: ballioli1@gmail.com
Classifier: Programming Language :: Python :: 3
Classifier: License :: OSI Approved :: MIT License
Classifier: Operating System :: OS Independent
Requires-Python: >=3.10
License-File: LICENSE
Requires-Dist: requests
